setup.cfg
setup.py
parsimony/__init__.py
parsimony/exceptions.py
parsimony/generate.py
parsimony/release.py
parsimony.egg-info/PKG-INFO
parsimony.egg-info/SOURCES.txt
parsimony.egg-info/dependency_links.txt
parsimony.egg-info/requires.txt
parsimony.egg-info/top_level.txt
parsimony/configuration/__init__.py
parsimony/configuration/configuration.py
parsimony/generators/__init__.py
parsimony/generators/callable_wrapper.py
parsimony/generators/file.py
parsimony/generators/generator.py
parsimony/persistence/SHA512_obfuscator.py
parsimony/persistence/__init__.py
parsimony/persistence/cache.py
parsimony/persistence/data_obfuscator.py
parsimony/persistence/in_memory.py
parsimony/persistence/object_store.py
parsimony/persistence/store.py